odoo/addons/mrp_production_serial_matrix/README.rst
odoo/addons/mrp_production_serial_matrix/__init__.py
odoo/addons/mrp_production_serial_matrix/__manifest__.py
odoo/addons/mrp_production_serial_matrix/i18n/mrp_production_serial_matrix.pot
odoo/addons/mrp_production_serial_matrix/models/__init__.py
odoo/addons/mrp_production_serial_matrix/models/mrp_production.py
odoo/addons/mrp_production_serial_matrix/readme/CONTRIBUTORS.rst
odoo/addons/mrp_production_serial_matrix/readme/DESCRIPTION.rst
odoo/addons/mrp_production_serial_matrix/readme/ROADMAP.rst
odoo/addons/mrp_production_serial_matrix/readme/USAGE.rst
odoo/addons/mrp_production_serial_matrix/security/ir.model.access.csv
odoo/addons/mrp_production_serial_matrix/static/description/icon.png
odoo/addons/mrp_production_serial_matrix/static/description/index.html
odoo/addons/mrp_production_serial_matrix/tests/__init__.py
odoo/addons/mrp_production_serial_matrix/tests/test_mrp_production_serial_matrix.py
odoo/addons/mrp_production_serial_matrix/views/mrp_production_views.xml
odoo/addons/mrp_production_serial_matrix/wizards/__init__.py
odoo/addons/mrp_production_serial_matrix/wizards/mrp_production_serial_matrix.py
odoo/addons/mrp_production_serial_matrix/wizards/mrp_production_serial_matrix_line.py
odoo/addons/mrp_production_serial_matrix/wizards/mrp_production_serial_matrix_view.xml
odoo14_addon_mrp_production_serial_matrix-14.0.1.1.0.dist-info/METADATA
odoo14_addon_mrp_production_serial_matrix-14.0.1.1.0.dist-info/WHEEL
odoo14_addon_mrp_production_serial_matrix-14.0.1.1.0.dist-info/top_level.txt
odoo14_addon_mrp_production_serial_matrix-14.0.1.1.0.dist-info/RECORD
